markitup/__init__.py
markitup/fields.py
markitup/markup.py
markitup/models.py
markitup/renderers.py
markitup/settings.py
markitup/urls.py
markitup/util.py
markitup/views.py
markitup/widgets.py
markitup/static/markitup/ajax_csrf.js
markitup/static/markitup/django-markitup.js
markitup/static/markitup/jquery.markitup.js
markitup/static/markitup/preview.css
markitup/static/markitup/sets/default/set.js
markitup/static/markitup/sets/default/style.css
markitup/static/markitup/sets/default/images/bold.png
markitup/static/markitup/sets/default/images/clean.png
markitup/static/markitup/sets/default/images/image.png
markitup/static/markitup/sets/default/images/italic.png
markitup/static/markitup/sets/default/images/link.png
markitup/static/markitup/sets/default/images/list-bullet.png
markitup/static/markitup/sets/default/images/list-numeric.png
markitup/static/markitup/sets/default/images/picture.png
markitup/static/markitup/sets/default/images/preview.png
markitup/static/markitup/sets/default/images/stroke.png
markitup/static/markitup/sets/markdown/readme.txt
markitup/static/markitup/sets/markdown/set.js
markitup/static/markitup/sets/markdown/style.css
markitup/static/markitup/sets/markdown/images/bold.png
markitup/static/markitup/sets/markdown/images/code.png
markitup/static/markitup/sets/markdown/images/h1.png
markitup/static/markitup/sets/markdown/images/h2.png
markitup/static/markitup/sets/markdown/images/h3.png
markitup/static/markitup/sets/markdown/images/h4.png
markitup/static/markitup/sets/markdown/images/h5.png
markitup/static/markitup/sets/markdown/images/h6.png
markitup/static/markitup/sets/markdown/images/italic.png
markitup/static/markitup/sets/markdown/images/link.png
markitup/static/markitup/sets/markdown/images/list-bullet.png
markitup/static/markitup/sets/markdown/images/list-numeric.png
markitup/static/markitup/sets/markdown/images/picture.png
markitup/static/markitup/sets/markdown/images/preview.png
markitup/static/markitup/sets/markdown/images/quotes.png
django_markitup-4.1.0.dist-info/AUTHORS.rst
django_markitup-4.1.0.dist-info/LICENSE.txt
django_markitup-4.1.0.dist-info/METADATA
django_markitup-4.1.0.dist-info/WHEEL
django_markitup-4.1.0.dist-info/top_level.txt
django_markitup-4.1.0.dist-info/RECORD
