Metadata-Version: 2.1
Name: django-markitup
Version: 4.1.0
Summary: Markup handling for Django using the MarkItUp! universal markup editor
Home-page: https://github.com/CTPUG/django-markitup
Author: Carl Meyer
Author-email: carl@oddbird.net
License: UNKNOWN
Platform: UNKNOWN
Classifier: Development Status :: 5 - Production/Stable
Classifier: Environment :: Web Environment
Classifier: Intended Audience :: Developers
Classifier: License :: OSI Approved :: BSD License
Classifier: Operating System :: OS Independent
Classifier: Programming Language :: Python
Classifier: Programming Language :: Python :: 3
Classifier: Programming Language :: Python :: 3.5
Classifier: Programming Language :: Python :: 3.6
Classifier: Programming Language :: Python :: 3.7
Classifier: Programming Language :: Python :: 3.8
Classifier: Framework :: Django
